[{"__symbolic":"module","version":4,"metadata":{"_add":{"__symbolic":"function"},"_suspend":{"__symbolic":"function"},"_pauseOthers":{"__symbolic":"function"},"_unpauseOthers":{"__symbolic":"function"},"_activate":{"__symbolic":"function"},"_deregister":{"__symbolic":"function"},"Hotkey":{"__symbolic":"function","parameters":["key","description","options"],"value":{"__symbolic":"error","message":"Lambda not supported","line":145,"character":9}},"HotkeysService":{"__symbolic":"class","decorators":[{"__symbolic":"call","expression":{"__symbolic":"reference","module":"@angular/core","name":"Injectable","line":169,"character":1}}],"members":{"__ctor__":[{"__symbolic":"constructor","parameters":[{"__symbolic":"reference","module":"@angular/core","name":"NgZone","line":179,"character":30}]}],"add":[{"__symbolic":"method"}]}}}}]