[{"__symbolic":"module","version":4,"metadata":{"NotificationModule":{"__symbolic":"class","decorators":[{"__symbolic":"call","expression":{"__symbolic":"reference","module":"@angular/core","name":"NgModule","line":9,"character":1},"arguments":[{"declarations":[{"__symbolic":"reference","module":"./notification.component","name":"NotificationComponent","line":10,"character":17},{"__symbolic":"reference","module":"./notification-container.component","name":"NotificationContainerComponent","line":10,"character":40}],"exports":[{"__symbolic":"reference","module":"./notification.component","name":"NotificationComponent","line":11,"character":12},{"__symbolic":"reference","module":"./notification-container.component","name":"NotificationContainerComponent","line":11,"character":35}],"providers":[{"__symbolic":"reference","module":"./notification.service","name":"NotificationService","line":12,"character":14},{"__symbolic":"reference","module":"../../services","name":"InjectionService","line":12,"character":35}],"imports":[{"__symbolic":"reference","module":"@angular/common","name":"CommonModule","line":13,"character":12}],"entryComponents":[{"__symbolic":"reference","module":"./notification.component","name":"NotificationComponent","line":14,"character":20},{"__symbolic":"reference","module":"./notification-container.component","name":"NotificationContainerComponent","line":14,"character":43}]}]}]}}}]