[{"__symbolic":"module","version":4,"metadata":{"SelectModule":{"__symbolic":"class","decorators":[{"__symbolic":"call","expression":{"__symbolic":"reference","module":"@angular/core","name":"NgModule"},"arguments":[{"declarations":[{"__symbolic":"reference","module":"./select.component","name":"SelectComponent"},{"__symbolic":"reference","module":"./select-input.component","name":"SelectInputComponent"},{"__symbolic":"reference","module":"./select-option.directive","name":"SelectOptionDirective"},{"__symbolic":"reference","module":"./select-option-template.directive","name":"SelectOptionTemplateDirective"},{"__symbolic":"reference","module":"./select-dropdown.component","name":"SelectDropdownComponent"},{"__symbolic":"reference","module":"./select-option-input-template.directive","name":"SelectOptionInputTemplateDirective"}],"exports":[{"__symbolic":"reference","module":"./select.component","name":"SelectComponent"},{"__symbolic":"reference","module":"./select-option.directive","name":"SelectOptionDirective"},{"__symbolic":"reference","module":"./select-option-template.directive","name":"SelectOptionTemplateDirective"},{"__symbolic":"reference","module":"./select-option-input-template.directive","name":"SelectOptionInputTemplateDirective"}],"imports":[{"__symbolic":"reference","module":"@angular/common","name":"CommonModule"}]}]}]}}}]