[{"__symbolic":"module","version":4,"metadata":{"SectionModule":{"__symbolic":"class","decorators":[{"__symbolic":"call","expression":{"__symbolic":"reference","module":"@angular/core","name":"NgModule"},"arguments":[{"declarations":[{"__symbolic":"reference","module":"./section.component","name":"SectionComponent"},{"__symbolic":"reference","module":"./section-header.component","name":"SectionHeaderComponent"}],"exports":[{"__symbolic":"reference","module":"./section.component","name":"SectionComponent"},{"__symbolic":"reference","module":"./section-header.component","name":"SectionHeaderComponent"}],"imports":[{"__symbolic":"reference","module":"@angular/common","name":"CommonModule"}]}]}]}}}]