[{"__symbolic":"module","version":4,"metadata":{"MinValidatorDirective":{"__symbolic":"class","decorators":[{"__symbolic":"call","expression":{"__symbolic":"reference","module":"@angular/core","name":"Directive","line":9,"character":1},"arguments":[{"selector":"input[min]","providers":[{"provide":{"__symbolic":"reference","module":"@angular/forms","name":"NG_VALIDATORS","line":4,"character":11},"useExisting":{"__symbolic":"reference","name":"MinValidatorDirective"},"multi":true}],"host":{"[attr.min]":"min ? min : null","[attr.type]":"type ? type : null","$quoted$":["[attr.min]","[attr.type]"]}}]}],"members":{"min":[{"__symbolic":"property","decorators":[{"__symbolic":"call","expression":{"__symbolic":"reference","module":"@angular/core","name":"Input","line":18,"character":3}}]}],"type":[{"__symbolic":"property","decorators":[{"__symbolic":"call","expression":{"__symbolic":"reference","module":"@angular/core","name":"Input","line":19,"character":3}}]}],"validate":[{"__symbolic":"method"}]}}}}]